QCAT_Basic/QCAT_Basic.py
QCAT_Basic/__init__.py
QCAT_Basic-0.0.4.dist-info/METADATA
QCAT_Basic-0.0.4.dist-info/RECORD
QCAT_Basic-0.0.4.dist-info/WHEEL
QCAT_Basic-0.0.4.dist-info/top_level.txt
