Metadata-Version: 2.1
Name: QCAT-Basic
Version: 0.0.4
Summary: A small package contains most useful QCAT interfaces
Home-page: https://github.com/weihuachen/python_qcat_apis
Author: Weihua Chen
Author-email: weihua.chen@gmail.com
License: UNKNOWN
Platform: UNKNOWN
Classifier: Programming Language :: Python :: 2.7
Classifier: License :: OSI Approved :: MIT License
Classifier: Operating System :: Microsoft :: Windows
